{
 "upstreams": [
     {
       "id": "center-a",
       "enable": true,
       "sip_id": "42010000101234567890",
       "realm": "houqinban.cn",
       "sip_ip": "192.168.110.110",
       "sip_port": 5060,
       "local_device_id": "34020000001320000001",
       "username": "",
       "password": "czykeith",
       "register_validity": 3600,
       "keepalive_interval": 60,
       "media_ip": "192.168.110.164",
       "media_port": 30000,
       "comment": "一级中心平台 A"
     }
   ],
   "subs": [
     {
       "upstream_id": "center-a",
       "stream_name": "test_stream",
       "channel_id": "34020000002000000001"
     }
  ]
}